s3_url/__init__.py
s3_url/s3_url.py
s3_url_helper-0.4.3.dist-info/licenses/LICENSE
s3_url_helper-0.4.3.dist-info/METADATA
s3_url_helper-0.4.3.dist-info/WHEEL
s3_url_helper-0.4.3.dist-info/top_level.txt
s3_url_helper-0.4.3.dist-info/RECORD
