Metadata-Version: 2.4
Name: s3_url_helper
Version: 0.4.3
Summary: S3Url is a helper class that can help with simple operations on AWS S3 objects
Author-email: Nikolai Orlov <nikolaiorl@gmail.com>
Project-URL: Homepage, https://github.com/n-orlov/s3-url-helper
Project-URL: Bug Tracker, https://github.com/n-orlov/s3-url-helper/issues
Classifier: Programming Language :: Python :: 3
Classifier: License :: OSI Approved :: MIT License
Classifier: Operating System :: OS Independent
Requires-Python: >=3.7
License-File: LICENSE
Requires-Dist: boto3
Provides-Extra: dev
Requires-Dist: pytest; extra == "dev"
Requires-Dist: pytest-cov; extra == "dev"
Requires-Dist: moto; extra == "dev"
Requires-Dist: pylint; extra == "dev"
Requires-Dist: assertpy; extra == "dev"
Provides-Extra: build
Requires-Dist: setuptools_scm; extra == "build"
Requires-Dist: twine; extra == "build"
Requires-Dist: build; extra == "build"
Dynamic: license-file
